csvbase/__init__.py
csvbase-0.1.1.dist-info/LICENSE
csvbase-0.1.1.dist-info/METADATA
csvbase-0.1.1.dist-info/WHEEL
csvbase-0.1.1.dist-info/top_level.txt
csvbase-0.1.1.dist-info/RECORD
