Metadata-Version: 2.1
Name: csvbase
Version: 0.1.1
Summary: A simple database with csv files
Home-page: https://github.com/bentoavb/csvbase
Author: Anderson Vitor Bento
Author-email: bentoavb@gmail.com
License: UNKNOWN
Platform: UNKNOWN
Classifier: Programming Language :: Python :: 3
Classifier: License :: OSI Approved :: MIT License
Classifier: Operating System :: OS Independent
